OpFlowLab/OpFlowLab.py
OpFlowLab/OpFlowLab_GUI.py
OpFlowLab/OpFlowLab_batch.py
OpFlowLab/__init__.py
OpFlowLab/version.py
OpFlowLab/GUI/XStream.py
OpFlowLab/GUI/__init__.py
OpFlowLab/GUI/aboutTab.py
OpFlowLab/GUI/advancedConfigTab.py
OpFlowLab/GUI/flowDerivativesTab.py
OpFlowLab/GUI/flowMatchTab.py
OpFlowLab/GUI/flowPathTab.py
OpFlowLab/GUI/flowTracerTab.py
OpFlowLab/GUI/flowWarpTab.py
OpFlowLab/GUI/imageViewerWidget.py
OpFlowLab/GUI/loadImageTab.py
OpFlowLab/GUI/loadVelocityTab.py
OpFlowLab/GUI/material_stylesheet.py
OpFlowLab/GUI/opFlowLabWorker.py
OpFlowLab/GUI/opticalFlowTab.py
OpFlowLab/GUI/pathWidget.py
OpFlowLab/GUI/styleSheet.py
OpFlowLab/GUI/nvidiaOFOptions/__init__.py
OpFlowLab/GUI/nvidiaOFOptions/nvidiaOptions.py
OpFlowLab/GUI/opticalFlow/__init__.py
OpFlowLab/GUI/opticalFlow/broxOptions.py
OpFlowLab/GUI/opticalFlow/dualOptions.py
OpFlowLab/GUI/opticalFlow/farnebackOptions.py
OpFlowLab/GUI/opticalFlow/nvidiaOptions.py
OpFlowLab/GUI/opticalFlow/pyrLKOptions.py
OpFlowLab/functions/__init__.py
OpFlowLab/functions/colormap_functions.py
OpFlowLab/functions/interpolation.py
OpFlowLab/functions/object_matching.py
OpFlowLab/functions/tracer_functions.py
OpFlowLab/functions/utils.py
OpFlowLab-0.1.1.dist-info/LICENSE
OpFlowLab-0.1.1.dist-info/METADATA
OpFlowLab-0.1.1.dist-info/WHEEL
OpFlowLab-0.1.1.dist-info/entry_points.txt
OpFlowLab-0.1.1.dist-info/top_level.txt
OpFlowLab-0.1.1.dist-info/RECORD
