Metadata-Version: 2.1
Name: OpFlowLab
Version: 0.1.1
Summary: GUI to facilitate the calculation of optical flow velocity fields in biological images
Home-page: https://gitlab.com/xianbin.yong13/OpFlowLab
Author: Xianbin Yong
Author-email: yong.xianbin@u.nus.edu
License: GPLv3
Project-URL: Documentation, https://opflowlab.readthedocs.io/
Project-URL: Research group, https://ctlimlab.org/
Project-URL: Source, https://gitlab.com/xianbin.yong13/OpFlowLab
Platform: UNKNOWN
Classifier: Intended Audience :: Science/Research
Classifier: Programming Language :: Python
Classifier: Programming Language :: Python :: 3
Classifier: Programming Language :: Python :: 3 :: Only
Classifier: Programming Language :: Python :: 3.7
Classifier: Programming Language :: Python :: 3.8
Classifier: Programming Language :: Python :: 3.9
Classifier: License :: OSI Approved :: GNU General Public License v3 (GPLv3)
Classifier: Operating System :: OS Independent
Classifier: Development Status :: 3 - Alpha
Classifier: Topic :: Scientific/Engineering
Requires-Python: >=3.7
License-File: LICENSE
Requires-Dist: opencv-python (>4.3.0)
Requires-Dist: numpy (>=1.17.0)
Requires-Dist: matplotlib (>=3.0.0)
Requires-Dist: numba (>=0.47.0)
Requires-Dist: scikit-image (>=0.17.1)
Requires-Dist: pykdtree (>=1.3.4)
Requires-Dist: scipy (>=1.5.0)
Requires-Dist: PyQt5 (>=5.9.2)
Requires-Dist: tqdm (>=4.40.0)
Requires-Dist: ruamel.yaml (>=0.16.0)
Requires-Dist: pyqtgraph (>=0.11.0)
Requires-Dist: QtAwesome (>=1.0.2)
Requires-Dist: flow-vis (>=0.1)
